ubuntuone_storageprotocol-1.0-py2.7-nspkg.pth
ubuntuone/storageprotocol/__init__.py
ubuntuone/storageprotocol/client.py
ubuntuone/storageprotocol/content_hash.py
ubuntuone/storageprotocol/context.py
ubuntuone/storageprotocol/delta.py
ubuntuone/storageprotocol/dircontent.py
ubuntuone/storageprotocol/dircontent_pb2.py
ubuntuone/storageprotocol/errors.py
ubuntuone/storageprotocol/protocol_pb2.py
ubuntuone/storageprotocol/proxy_tunnel.py
ubuntuone/storageprotocol/public_file_info.py
ubuntuone/storageprotocol/request.py
ubuntuone/storageprotocol/sharersp.py
ubuntuone/storageprotocol/utils.py
ubuntuone/storageprotocol/validators.py
ubuntuone/storageprotocol/volumes.py
ubuntuone/storageprotocol/tests/__init__.py
ubuntuone/storageprotocol/tests/test_bytesproducer.py
ubuntuone/storageprotocol/tests/test_client.py
ubuntuone/storageprotocol/tests/test_context.py
ubuntuone/storageprotocol/tests/test_delta_info.py
ubuntuone/storageprotocol/tests/test_dircontent.py
ubuntuone/storageprotocol/tests/test_errors.py
ubuntuone/storageprotocol/tests/test_hashes.py
ubuntuone/storageprotocol/tests/test_proxy_tunnel.py
ubuntuone/storageprotocol/tests/test_public_file_info.py
ubuntuone/storageprotocol/tests/test_putcontent.py
ubuntuone/storageprotocol/tests/test_query.py
ubuntuone/storageprotocol/tests/test_request.py
ubuntuone/storageprotocol/tests/test_sharersp.py
ubuntuone/storageprotocol/tests/test_throttling.py
ubuntuone/storageprotocol/tests/test_volumes.py
ubuntuone_storageprotocol-1.0.dist-info/METADATA
ubuntuone_storageprotocol-1.0.dist-info/RECORD
ubuntuone_storageprotocol-1.0.dist-info/WHEEL
ubuntuone_storageprotocol-1.0.dist-info/namespace_packages.txt
ubuntuone_storageprotocol-1.0.dist-info/top_level.txt
