Metadata-Version: 2.1
Name: ubuntuone-storageprotocol
Version: 1.0
Summary: The protocol implementation for the Magicicada filesync server (open source fork of the Ubuntu One filesync).
Home-page: UNKNOWN
Author: UNKNOWN
Author-email: UNKNOWN
License: UNKNOWN
Platform: UNKNOWN
Requires-Dist: pyOpenSSL
Requires-Dist: protobuf
Requires-Dist: service-identity
Requires-Dist: twisted
Requires-Dist: zope.interface
